azext_managementgroups/__init__.py
azext_managementgroups/_client_factory.py
azext_managementgroups/_exception_handler.py
azext_managementgroups/_help.py
azext_managementgroups/_params.py
azext_managementgroups/commands.py
azext_managementgroups/custom.py
azext_managementgroups/managementgroups/__init__.py
azext_managementgroups/managementgroups/management_groups_api.py
azext_managementgroups/managementgroups/version.py
azext_managementgroups/managementgroups/models/__init__.py
azext_managementgroups/managementgroups/models/create_management_group_request.py
azext_managementgroups/managementgroups/models/error_details.py
azext_managementgroups/managementgroups/models/error_response.py
azext_managementgroups/managementgroups/models/management_group.py
azext_managementgroups/managementgroups/models/management_group_child_info.py
azext_managementgroups/managementgroups/models/management_group_details.py
azext_managementgroups/managementgroups/models/management_group_info.py
azext_managementgroups/managementgroups/models/management_group_info_paged.py
azext_managementgroups/managementgroups/models/operation.py
azext_managementgroups/managementgroups/models/operation_display.py
azext_managementgroups/managementgroups/models/operation_paged.py
azext_managementgroups/managementgroups/models/parent_group_info.py
azext_managementgroups/managementgroups/operations/__init__.py
azext_managementgroups/managementgroups/operations/management_group_subscriptions_operations.py
azext_managementgroups/managementgroups/operations/management_groups_operations.py
azext_managementgroups/managementgroups/operations/operations.py
managementgroups-0.1.0.dist-info/DESCRIPTION.rst
managementgroups-0.1.0.dist-info/METADATA
managementgroups-0.1.0.dist-info/RECORD
managementgroups-0.1.0.dist-info/WHEEL
managementgroups-0.1.0.dist-info/metadata.json
managementgroups-0.1.0.dist-info/top_level.txt
